otree_redwood/__init__.py
otree_redwood/abstract_views.py
otree_redwood/apps.py
otree_redwood/consumers.py
otree_redwood/models.py
otree_redwood/views.py
otree_redwood/firebase/__init__.py
otree_redwood/firebase/events.py
otree_redwood/firebase/ticks.py
otree_redwood/firebase/watch.py
otree_redwood/otree_extensions/__init__.py
otree_redwood/otree_extensions/admin.py
otree_redwood/otree_extensions/routing.py
otree_redwood/static/bower_components/app-storage/.bower.json
otree_redwood/static/bower_components/app-storage/.gitignore
otree_redwood/static/bower_components/app-storage/CONTRIBUTING.md
otree_redwood/static/bower_components/app-storage/README.md
otree_redwood/static/bower_components/app-storage/app-network-status-behavior.html
otree_redwood/static/bower_components/app-storage/app-storage-behavior.html
otree_redwood/static/bower_components/app-storage/bower.json
otree_redwood/static/bower_components/app-storage/index.html
otree_redwood/static/bower_components/app-storage/.github/ISSUE_TEMPLATE.md
otree_redwood/static/bower_components/app-storage/app-indexeddb-mirror/app-indexeddb-mirror-client.html
otree_redwood/static/bower_components/app-storage/app-indexeddb-mirror/app-indexeddb-mirror-worker.js
otree_redwood/static/bower_components/app-storage/app-indexeddb-mirror/app-indexeddb-mirror.html
otree_redwood/static/bower_components/app-storage/app-indexeddb-mirror/common-worker-scope.js
otree_redwood/static/bower_components/app-storage/app-indexeddb-mirror/common-worker.html
otree_redwood/static/bower_components/app-storage/app-localstorage/app-localstorage-document.html
otree_redwood/static/bower_components/app-storage/test/app-storage-compatibility-suite.html
otree_redwood/static/bower_components/app-storage/test/app-storage.html
otree_redwood/static/bower_components/app-storage/test/index.html
otree_redwood/static/bower_components/app-storage/test/app-indexeddb-mirror/app-indexeddb-mirror.html
otree_redwood-0.1.1.dist-info/DESCRIPTION.rst
otree_redwood-0.1.1.dist-info/METADATA
otree_redwood-0.1.1.dist-info/RECORD
otree_redwood-0.1.1.dist-info/WHEEL
otree_redwood-0.1.1.dist-info/metadata.json
otree_redwood-0.1.1.dist-info/top_level.txt
