Metadata-Version: 2.0
Name: otree-redwood
Version: 0.1.1
Summary: oTree extension for inter-page communication.
Home-page: https://github.com/Leeps-Lab/otree-redwood
Author: James Pettit
Author-email: james.l.pettit@gmail.com
License: MIT License
Platform: UNKNOWN
Classifier: Environment :: Web Environment
Classifier: Framework :: Django
Classifier: Intended Audience :: Developers
Classifier: License :: OSI Approved :: MIT License
Classifier: Operating System :: OS Independent
Classifier: Programming Language :: Python
Classifier: Programming Language :: Python :: 3
Classifier: Programming Language :: Python :: 3.4
Classifier: Programming Language :: Python :: 3.5
Classifier: Topic :: Internet :: WWW/HTTP
Classifier: Topic :: Internet :: WWW/HTTP :: Dynamic Content
Requires-Dist: asgi-redis (>=1.2.0,<2)
Requires-Dist: channels (>=1.1.3,<2)
Requires-Dist: daphne (>=1.0.0,<2)
